pkhelper/__init__.py
pkhelper/aiohttp_download.py
pkhelper/bash_cmds.py
pkhelper/cli.py
pkhelper/ffmpeg.py
pkhelper/ffmpeg_utils.py
pkhelper/gdown_helper.py
pkhelper/github_repo_direct_link.py
pkhelper/gofile_up.py
pkhelper/pzhe.py
pkhelper/utils.py
pkhelper/youtube.py
pkhelper-0.0.36.dist-info/LICENSE
pkhelper-0.0.36.dist-info/METADATA
pkhelper-0.0.36.dist-info/WHEEL
pkhelper-0.0.36.dist-info/entry_points.txt
pkhelper-0.0.36.dist-info/top_level.txt
pkhelper-0.0.36.dist-info/RECORD
