Metadata-Version: 2.1
Name: pkhelper
Version: 0.0.36
Summary: A module for some common things
Home-page: https://github.com/pk-628996/pkhelper
Download-URL: https://github.com/pk-628996/pkhelper/archive/refs/tags/v0.0.36-alpha.zip
License: MIT
License-File: LICENSE
Requires-Dist: requests
Requires-Dist: gdown
Requires-Dist: aiohttp
Requires-Dist: cloudscraper
Requires-Dist: beautifulsoup4
Requires-Dist: youtube-transcript-api
